{
	"@programName": "ZAP",
	"@version": "2.17.0",
	"@generated": "Sat, 3 Jan 2026 09:32:26",
	"created": "2026-01-03T09:32:26.276094044Z",
	"insights":[
		{
			"level": "Info",
			"reason": "Informational",
			"site": "https://dls03qes9fc77.cloudfront.net",
			"key": "insight.code.2xx",
			"description": "Percentage of responses with status code 2xx",
			"statistic": "9"
		},
		{
			"level": "Info",
			"reason": "Informational",
			"site": "https://dls03qes9fc77.cloudfront.net",
			"key": "insight.code.3xx",
			"description": "Percentage of responses with status code 3xx",
			"statistic": "6"
		},
		{
			"level": "Info",
			"reason": "Informational",
			"site": "https://dls03qes9fc77.cloudfront.net",
			"key": "insight.code.4xx",
			"description": "Percentage of responses with status code 4xx",
			"statistic": "83"
		},
		{
			"level": "Info",
			"reason": "Informational",
			"site": "https://dls03qes9fc77.cloudfront.net",
			"key": "insight.endpoint.ctype.application/json",
			"description": "Percentage of endpoints with content type application/json",
			"statistic": "80"
		},
		{
			"level": "Info",
			"reason": "Informational",
			"site": "https://dls03qes9fc77.cloudfront.net",
			"key": "insight.endpoint.ctype.text/html",
			"description": "Percentage of endpoints with content type text/html",
			"statistic": "19"
		},
		{
			"level": "Info",
			"reason": "Informational",
			"site": "https://dls03qes9fc77.cloudfront.net",
			"key": "insight.endpoint.method.DELETE",
			"description": "Percentage of endpoints with method DELETE",
			"statistic": "4"
		},
		{
			"level": "Info",
			"reason": "Informational",
			"site": "https://dls03qes9fc77.cloudfront.net",
			"key": "insight.endpoint.method.GET",
			"description": "Percentage of endpoints with method GET",
			"statistic": "69"
		},
		{
			"level": "Info",
			"reason": "Informational",
			"site": "https://dls03qes9fc77.cloudfront.net",
			"key": "insight.endpoint.method.PATCH",
			"description": "Percentage of endpoints with method PATCH",
			"statistic": "8"
		},
		{
			"level": "Info",
			"reason": "Informational",
			"site": "https://dls03qes9fc77.cloudfront.net",
			"key": "insight.endpoint.method.POST",
			"description": "Percentage of endpoints with method POST",
			"statistic": "16"
		},
		{
			"level": "Info",
			"reason": "Informational",
			"site": "https://dls03qes9fc77.cloudfront.net",
			"key": "insight.endpoint.total",
			"description": "Count of total endpoints",
			"statistic": "89"
		},
		{
			"level": "Info",
			"reason": "Informational",
			"site": "https://dls03qes9fc77.cloudfront.net",
			"key": "insight.response.slow",
			"description": "Percentage of slow responses",
			"statistic": "34"
		}
	],
	"site":[ 
		{
			"@name": "https://dls03qes9fc77.cloudfront.net",
			"@host": "dls03qes9fc77.cloudfront.net",
			"@port": "443",
			"@ssl": "true",
			"alerts": [ 
				{
					"pluginid": "10038",
					"alertRef": "10038-1",
					"alert": "Content Security Policy (CSP) Header Not Set",
					"name": "Content Security Policy (CSP) Header Not Set",
					"riskcode": "2",
					"confidence": "3",
					"riskdesc": "Medium (High)",
					"desc": "<p>Content Security Policy (CSP) is an added layer of security that helps to detect and mitigate certain types of attacks, including Cross Site Scripting (XSS) and data injection attacks. These attacks are used for everything from data theft to site defacement or distribution of malware. CSP provides a set of standard HTTP headers that allow website owners to declare approved sources of content that browsers should be allowed to load on that page \u2014 covered types are JavaScript, CSS, HTML frames, fonts, images and embeddable objects such as Java applets, ActiveX, audio and video files.</p>",
					"instances":[ 
						{
							"id": "13",
							"uri": "https://dls03qes9fc77.cloudfront.net/health",
							"nodeName": "https:\/\/dls03qes9fc77.cloudfront.net\/health",
							"method": "GET",
							"param": "",
							"attack": "",
							"evidence": "",
							"otherinfo": ""
						},
						{
							"id": "26",
							"uri": "https://dls03qes9fc77.cloudfront.net/metrics/cache",
							"nodeName": "https:\/\/dls03qes9fc77.cloudfront.net\/metrics\/cache",
							"method": "GET",
							"param": "",
							"attack": "",
							"evidence": "",
							"otherinfo": ""
						},
						{
							"id": "14",
							"uri": "https://dls03qes9fc77.cloudfront.net/ready",
							"nodeName": "https:\/\/dls03qes9fc77.cloudfront.net\/ready",
							"method": "GET",
							"param": "",
							"attack": "",
							"evidence": "",
							"otherinfo": ""
						}
					],
					"count": "3",
					"systemic": true,
					"solution": "<p>Ensure that your web server, application server, load balancer, etc. is configured to set the Content-Security-Policy header.</p>",
					"otherinfo": "",
					"reference": "<p>https://developer.mozilla.org/en-US/docs/Web/HTTP/Guides/CSP</p><p>https://cheatsheetseries.owasp.org/cheatsheets/Content_Security_Policy_Cheat_Sheet.html</p><p>https://www.w3.org/TR/CSP/</p><p>https://w3c.github.io/webappsec-csp/</p><p>https://web.dev/articles/csp</p><p>https://caniuse.com/#feat=contentsecuritypolicy</p><p>https://content-security-policy.com/</p>",
					"cweid": "693",
					"wascid": "15",
					"sourceid": "5"
				},
				{
					"pluginid": "10063",
					"alertRef": "10063-1",
					"alert": "Permissions Policy Header Not Set",
					"name": "Permissions Policy Header Not Set",
					"riskcode": "1",
					"confidence": "2",
					"riskdesc": "Low (Medium)",
					"desc": "<p>Permissions Policy Header is an added layer of security that helps to restrict from unauthorized access or usage of browser/client features by web resources. This policy ensures the user privacy by limiting or specifying the features of the browsers can be used by the web resources. Permissions Policy provides a set of standard HTTP headers that allow website owners to limit which features of browsers can be used by the page such as camera, microphone, location, full screen etc.</p>",
					"instances":[ 
						{
							"id": "25",
							"uri": "https://dls03qes9fc77.cloudfront.net/health",
							"nodeName": "https:\/\/dls03qes9fc77.cloudfront.net\/health",
							"method": "GET",
							"param": "",
							"attack": "",
							"evidence": "",
							"otherinfo": ""
						},
						{
							"id": "34",
							"uri": "https://dls03qes9fc77.cloudfront.net/metrics/cache",
							"nodeName": "https:\/\/dls03qes9fc77.cloudfront.net\/metrics\/cache",
							"method": "GET",
							"param": "",
							"attack": "",
							"evidence": "",
							"otherinfo": ""
						},
						{
							"id": "24",
							"uri": "https://dls03qes9fc77.cloudfront.net/ready",
							"nodeName": "https:\/\/dls03qes9fc77.cloudfront.net\/ready",
							"method": "GET",
							"param": "",
							"attack": "",
							"evidence": "",
							"otherinfo": ""
						}
					],
					"count": "3",
					"systemic": true,
					"solution": "<p>Ensure that your web server, application server, load balancer, etc. is configured to set the Permissions-Policy header.</p>",
					"otherinfo": "",
					"reference": "<p>https://developer.mozilla.org/en-US/docs/Web/HTTP/Reference/Headers/Permissions-Policy</p><p>https://developer.chrome.com/blog/feature-policy/</p><p>https://scotthelme.co.uk/a-new-security-header-feature-policy/</p><p>https://w3c.github.io/webappsec-feature-policy/</p><p>https://www.smashingmagazine.com/2018/12/feature-policy/</p>",
					"cweid": "693",
					"wascid": "15",
					"sourceid": "5"
				},
				{
					"pluginid": "10037",
					"alertRef": "10037",
					"alert": "Server Leaks Information via \"X-Powered-By\" HTTP Response Header Field(s)",
					"name": "Server Leaks Information via \"X-Powered-By\" HTTP Response Header Field(s)",
					"riskcode": "1",
					"confidence": "2",
					"riskdesc": "Low (Medium)",
					"desc": "<p>The web/application server is leaking information via one or more \"X-Powered-By\" HTTP response headers. Access to such information may facilitate attackers identifying other frameworks/components your web application is reliant upon and the vulnerabilities such components may be subject to.</p>",
					"instances":[ 
						{
							"id": "21",
							"uri": "https://dls03qes9fc77.cloudfront.net/health",
							"nodeName": "https:\/\/dls03qes9fc77.cloudfront.net\/health",
							"method": "GET",
							"param": "",
							"attack": "",
							"evidence": "X-Powered-By: Next.js",
							"otherinfo": ""
						},
						{
							"id": "32",
							"uri": "https://dls03qes9fc77.cloudfront.net/metrics/cache",
							"nodeName": "https:\/\/dls03qes9fc77.cloudfront.net\/metrics\/cache",
							"method": "GET",
							"param": "",
							"attack": "",
							"evidence": "X-Powered-By: Next.js",
							"otherinfo": ""
						},
						{
							"id": "19",
							"uri": "https://dls03qes9fc77.cloudfront.net/ready",
							"nodeName": "https:\/\/dls03qes9fc77.cloudfront.net\/ready",
							"method": "GET",
							"param": "",
							"attack": "",
							"evidence": "X-Powered-By: Next.js",
							"otherinfo": ""
						}
					],
					"count": "3",
					"systemic": true,
					"solution": "<p>Ensure that your web server, application server, load balancer, etc. is configured to suppress \"X-Powered-By\" headers.</p>",
					"otherinfo": "",
					"reference": "<p>https://owasp.org/www-project-web-security-testing-guide/v42/4-Web_Application_Security_Testing/01-Information_Gathering/08-Fingerprint_Web_Application_Framework</p><p>https://www.troyhunt.com/shhh-dont-let-your-response-headers/</p>",
					"cweid": "497",
					"wascid": "13",
					"sourceid": "5"
				},
				{
					"pluginid": "10035",
					"alertRef": "10035-1",
					"alert": "Strict-Transport-Security Header Not Set",
					"name": "Strict-Transport-Security Header Not Set",
					"riskcode": "1",
					"confidence": "3",
					"riskdesc": "Low (High)",
					"desc": "<p>HTTP Strict Transport Security (HSTS) is a web security policy mechanism whereby a web server declares that complying user agents (such as a web browser) are to interact with it using only secure HTTPS connections (i.e. HTTP layered over TLS/SSL). HSTS is an IETF standards track protocol and is specified in RFC 6797.</p>",
					"instances":[ 
						{
							"id": "18",
							"uri": "https://dls03qes9fc77.cloudfront.net/health",
							"nodeName": "https:\/\/dls03qes9fc77.cloudfront.net\/health",
							"method": "GET",
							"param": "",
							"attack": "",
							"evidence": "",
							"otherinfo": ""
						},
						{
							"id": "30",
							"uri": "https://dls03qes9fc77.cloudfront.net/metrics/cache",
							"nodeName": "https:\/\/dls03qes9fc77.cloudfront.net\/metrics\/cache",
							"method": "GET",
							"param": "",
							"attack": "",
							"evidence": "",
							"otherinfo": ""
						},
						{
							"id": "17",
							"uri": "https://dls03qes9fc77.cloudfront.net/ready",
							"nodeName": "https:\/\/dls03qes9fc77.cloudfront.net\/ready",
							"method": "GET",
							"param": "",
							"attack": "",
							"evidence": "",
							"otherinfo": ""
						}
					],
					"count": "3",
					"systemic": true,
					"solution": "<p>Ensure that your web server, application server, load balancer, etc. is configured to enforce Strict-Transport-Security.</p>",
					"otherinfo": "",
					"reference": "<p>https://cheatsheetseries.owasp.org/cheatsheets/HTTP_Strict_Transport_Security_Cheat_Sheet.html</p><p>https://owasp.org/www-community/Security_Headers</p><p>https://en.wikipedia.org/wiki/HTTP_Strict_Transport_Security</p><p>https://caniuse.com/stricttransportsecurity</p><p>https://datatracker.ietf.org/doc/html/rfc6797</p>",
					"cweid": "319",
					"wascid": "15",
					"sourceid": "5"
				},
				{
					"pluginid": "10096",
					"alertRef": "10096",
					"alert": "Timestamp Disclosure - Unix",
					"name": "Timestamp Disclosure - Unix",
					"riskcode": "1",
					"confidence": "1",
					"riskdesc": "Low (Low)",
					"desc": "<p>A timestamp was disclosed by the application/web server. - Unix</p>",
					"instances":[ 
						{
							"id": "50",
							"uri": "https://dls03qes9fc77.cloudfront.net/api/catalog/products",
							"nodeName": "https:\/\/dls03qes9fc77.cloudfront.net\/api\/catalog\/products",
							"method": "GET",
							"param": "",
							"attack": "",
							"evidence": "1542272604",
							"otherinfo": "1542272604, which evaluates to: 2018-11-15 09:03:24."
						},
						{
							"id": "52",
							"uri": "https://dls03qes9fc77.cloudfront.net/api/catalog/products",
							"nodeName": "https:\/\/dls03qes9fc77.cloudfront.net\/api\/catalog\/products",
							"method": "GET",
							"param": "",
							"attack": "",
							"evidence": "1542291026",
							"otherinfo": "1542291026, which evaluates to: 2018-11-15 14:10:26."
						},
						{
							"id": "53",
							"uri": "https://dls03qes9fc77.cloudfront.net/api/catalog/products",
							"nodeName": "https:\/\/dls03qes9fc77.cloudfront.net\/api\/catalog\/products",
							"method": "GET",
							"param": "",
							"attack": "",
							"evidence": "1544716278",
							"otherinfo": "1544716278, which evaluates to: 2018-12-13 15:51:18."
						},
						{
							"id": "51",
							"uri": "https://dls03qes9fc77.cloudfront.net/api/catalog/products",
							"nodeName": "https:\/\/dls03qes9fc77.cloudfront.net\/api\/catalog\/products",
							"method": "GET",
							"param": "",
							"attack": "",
							"evidence": "1551028719",
							"otherinfo": "1551028719, which evaluates to: 2019-02-24 17:18:39."
						},
						{
							"id": "66",
							"uri": "https://dls03qes9fc77.cloudfront.net/api/search/popular",
							"nodeName": "https:\/\/dls03qes9fc77.cloudfront.net\/api\/search\/popular",
							"method": "GET",
							"param": "",
							"attack": "",
							"evidence": "1542272604",
							"otherinfo": "1542272604, which evaluates to: 2018-11-15 09:03:24."
						}
					],
					"count": "5",
					"systemic": true,
					"solution": "<p>Manually confirm that the timestamp data is not sensitive, and that the data cannot be aggregated to disclose exploitable patterns.</p>",
					"otherinfo": "<p>1542272604, which evaluates to: 2018-11-15 09:03:24.</p>",
					"reference": "<p>https://cwe.mitre.org/data/definitions/200.html</p>",
					"cweid": "497",
					"wascid": "13",
					"sourceid": "23"
				},
				{
					"pluginid": "100001",
					"alertRef": "100001",
					"alert": "Unexpected Content-Type was returned",
					"name": "Unexpected Content-Type was returned",
					"riskcode": "1",
					"confidence": "3",
					"riskdesc": "Low (High)",
					"desc": "<p>A Content-Type of text/html was returned by the server.</p><p>This is not one of the types expected to be returned by an API.</p><p>Raised by the 'Alert on Unexpected Content Types' script</p>",
					"instances":[ 
						{
							"id": "79",
							"uri": "https://dls03qes9fc77.cloudfront.net",
							"nodeName": "https:\/\/dls03qes9fc77.cloudfront.net",
							"method": "GET",
							"param": "",
							"attack": "",
							"evidence": "text/html",
							"otherinfo": ""
						},
						{
							"id": "204",
							"uri": "https://dls03qes9fc77.cloudfront.net/",
							"nodeName": "https:\/\/dls03qes9fc77.cloudfront.net\/",
							"method": "GET",
							"param": "",
							"attack": "",
							"evidence": "text/html",
							"otherinfo": ""
						},
						{
							"id": "65",
							"uri": "https://dls03qes9fc77.cloudfront.net/4698689398718167090",
							"nodeName": "https:\/\/dls03qes9fc77.cloudfront.net\/4698689398718167090",
							"method": "GET",
							"param": "",
							"attack": "",
							"evidence": "text/html",
							"otherinfo": ""
						},
						{
							"id": "221",
							"uri": "https://dls03qes9fc77.cloudfront.net/api/docs/",
							"nodeName": "https:\/\/dls03qes9fc77.cloudfront.net\/api\/docs\/",
							"method": "GET",
							"param": "",
							"attack": "",
							"evidence": "text/html",
							"otherinfo": ""
						},
						{
							"id": "220",
							"uri": "https://dls03qes9fc77.cloudfront.net/api/docs/static/index.html",
							"nodeName": "https:\/\/dls03qes9fc77.cloudfront.net\/api\/docs\/static\/index.html",
							"method": "GET",
							"param": "",
							"attack": "",
							"evidence": "text/html",
							"otherinfo": ""
						},
						{
							"id": "156",
							"uri": "https://dls03qes9fc77.cloudfront.net/computeMetadata/v1/",
							"nodeName": "https:\/\/dls03qes9fc77.cloudfront.net\/computeMetadata\/v1\/",
							"method": "GET",
							"param": "",
							"attack": "",
							"evidence": "text/html",
							"otherinfo": ""
						},
						{
							"id": "3",
							"uri": "https://dls03qes9fc77.cloudfront.net/health",
							"nodeName": "https:\/\/dls03qes9fc77.cloudfront.net\/health",
							"method": "GET",
							"param": "",
							"attack": "",
							"evidence": "text/html",
							"otherinfo": ""
						},
						{
							"id": "235",
							"uri": "https://dls03qes9fc77.cloudfront.net/health/",
							"nodeName": "https:\/\/dls03qes9fc77.cloudfront.net\/health\/",
							"method": "GET",
							"param": "",
							"attack": "",
							"evidence": "text/html",
							"otherinfo": ""
						},
						{
							"id": "152",
							"uri": "https://dls03qes9fc77.cloudfront.net/latest/meta-data/",
							"nodeName": "https:\/\/dls03qes9fc77.cloudfront.net\/latest\/meta-data\/",
							"method": "GET",
							"param": "",
							"attack": "",
							"evidence": "text/html",
							"otherinfo": ""
						},
						{
							"id": "168",
							"uri": "https://dls03qes9fc77.cloudfront.net/metadata/instance",
							"nodeName": "https:\/\/dls03qes9fc77.cloudfront.net\/metadata\/instance",
							"method": "GET",
							"param": "",
							"attack": "",
							"evidence": "text/html",
							"otherinfo": ""
						},
						{
							"id": "87",
							"uri": "https://dls03qes9fc77.cloudfront.net/metrics",
							"nodeName": "https:\/\/dls03qes9fc77.cloudfront.net\/metrics",
							"method": "GET",
							"param": "",
							"attack": "",
							"evidence": "text/html",
							"otherinfo": ""
						},
						{
							"id": "247",
							"uri": "https://dls03qes9fc77.cloudfront.net/metrics/",
							"nodeName": "https:\/\/dls03qes9fc77.cloudfront.net\/metrics\/",
							"method": "GET",
							"param": "",
							"attack": "",
							"evidence": "text/html",
							"otherinfo": ""
						},
						{
							"id": "78",
							"uri": "https://dls03qes9fc77.cloudfront.net/metrics/4835326925883131267",
							"nodeName": "https:\/\/dls03qes9fc77.cloudfront.net\/metrics\/4835326925883131267",
							"method": "GET",
							"param": "",
							"attack": "",
							"evidence": "text/html",
							"otherinfo": ""
						},
						{
							"id": "7",
							"uri": "https://dls03qes9fc77.cloudfront.net/metrics/cache",
							"nodeName": "https:\/\/dls03qes9fc77.cloudfront.net\/metrics\/cache",
							"method": "GET",
							"param": "",
							"attack": "",
							"evidence": "text/html",
							"otherinfo": ""
						},
						{
							"id": "243",
							"uri": "https://dls03qes9fc77.cloudfront.net/metrics/cache/",
							"nodeName": "https:\/\/dls03qes9fc77.cloudfront.net\/metrics\/cache\/",
							"method": "GET",
							"param": "",
							"attack": "",
							"evidence": "text/html",
							"otherinfo": ""
						},
						{
							"id": "160",
							"uri": "https://dls03qes9fc77.cloudfront.net/opc/v1/instance/",
							"nodeName": "https:\/\/dls03qes9fc77.cloudfront.net\/opc\/v1\/instance\/",
							"method": "GET",
							"param": "",
							"attack": "",
							"evidence": "text/html",
							"otherinfo": ""
						},
						{
							"id": "5",
							"uri": "https://dls03qes9fc77.cloudfront.net/ready",
							"nodeName": "https:\/\/dls03qes9fc77.cloudfront.net\/ready",
							"method": "GET",
							"param": "",
							"attack": "",
							"evidence": "text/html",
							"otherinfo": ""
						},
						{
							"id": "239",
							"uri": "https://dls03qes9fc77.cloudfront.net/ready/",
							"nodeName": "https:\/\/dls03qes9fc77.cloudfront.net\/ready\/",
							"method": "GET",
							"param": "",
							"attack": "",
							"evidence": "text/html",
							"otherinfo": ""
						}
					],
					"count": "18",
					"systemic": false,
					"solution": "",
					"otherinfo": "",
					"reference": "",
					"cweid": "-1",
					"wascid": "-1",
					"sourceid": "67"
				},
				{
					"pluginid": "100000",
					"alertRef": "100000",
					"alert": "A Client Error response code was returned by the server",
					"name": "A Client Error response code was returned by the server",
					"riskcode": "0",
					"confidence": "3",
					"riskdesc": "Informational (High)",
					"desc": "<p>A response code of 401 was returned by the server.</p><p>This may indicate that the application is failing to handle unexpected input correctly.</p><p>Raised by the 'Alert on HTTP Response Code Error' script</p>",
					"instances":[ 
						{
							"id": "39",
							"uri": "https://dls03qes9fc77.cloudfront.net/api/catalog/categories/id",
							"nodeName": "https:\/\/dls03qes9fc77.cloudfront.net\/api\/catalog\/categories\/id",
							"method": "DELETE",
							"param": "",
							"attack": "",
							"evidence": "401",
							"otherinfo": ""
						},
						{
							"id": "192",
							"uri": "https://dls03qes9fc77.cloudfront.net/api/catalog/categories/id/",
							"nodeName": "https:\/\/dls03qes9fc77.cloudfront.net\/api\/catalog\/categories\/id\/",
							"method": "DELETE",
							"param": "",
							"attack": "",
							"evidence": "404",
							"otherinfo": ""
						},
						{
							"id": "43",
							"uri": "https://dls03qes9fc77.cloudfront.net/api/catalog/products/id",
							"nodeName": "https:\/\/dls03qes9fc77.cloudfront.net\/api\/catalog\/products\/id",
							"method": "DELETE",
							"param": "",
							"attack": "",
							"evidence": "401",
							"otherinfo": ""
						},
						{
							"id": "198",
							"uri": "https://dls03qes9fc77.cloudfront.net/api/catalog/products/id/",
							"nodeName": "https:\/\/dls03qes9fc77.cloudfront.net\/api\/catalog\/products\/id\/",
							"method": "DELETE",
							"param": "",
							"attack": "",
							"evidence": "404",
							"otherinfo": ""
						},
						{
							"id": "63",
							"uri": "https://dls03qes9fc77.cloudfront.net/4698689398718167090",
							"nodeName": "https:\/\/dls03qes9fc77.cloudfront.net\/4698689398718167090",
							"method": "GET",
							"param": "",
							"attack": "",
							"evidence": "404",
							"otherinfo": ""
						},
						{
							"id": "80",
							"uri": "https://dls03qes9fc77.cloudfront.net/api",
							"nodeName": "https:\/\/dls03qes9fc77.cloudfront.net\/api",
							"method": "GET",
							"param": "",
							"attack": "",
							"evidence": "404",
							"otherinfo": ""
						},
						{
							"id": "206",
							"uri": "https://dls03qes9fc77.cloudfront.net/api/",
							"nodeName": "https:\/\/dls03qes9fc77.cloudfront.net\/api\/",
							"method": "GET",
							"param": "",
							"attack": "",
							"evidence": "404",
							"otherinfo": ""
						},
						{
							"id": "67",
							"uri": "https://dls03qes9fc77.cloudfront.net/api/3723237208397728523",
							"nodeName": "https:\/\/dls03qes9fc77.cloudfront.net\/api\/3723237208397728523",
							"method": "GET",
							"param": "",
							"attack": "",
							"evidence": "404",
							"otherinfo": ""
						},
						{
							"id": "81",
							"uri": "https://dls03qes9fc77.cloudfront.net/api/auth",
							"nodeName": "https:\/\/dls03qes9fc77.cloudfront.net\/api\/auth",
							"method": "GET",
							"param": "",
							"attack": "",
							"evidence": "404",
							"otherinfo": ""
						},
						{
							"id": "208",
							"uri": "https://dls03qes9fc77.cloudfront.net/api/auth/",
							"nodeName": "https:\/\/dls03qes9fc77.cloudfront.net\/api\/auth\/",
							"method": "GET",
							"param": "",
							"attack": "",
							"evidence": "404",
							"otherinfo": ""
						},
						{
							"id": "68",
							"uri": "https://dls03qes9fc77.cloudfront.net/api/auth/1228821100495706953",
							"nodeName": "https:\/\/dls03qes9fc77.cloudfront.net\/api\/auth\/1228821100495706953",
							"method": "GET",
							"param": "",
							"attack": "",
							"evidence": "404",
							"otherinfo": ""
						},
						{
							"id": "10",
							"uri": "https://dls03qes9fc77.cloudfront.net/api/auth/me",
							"nodeName": "https:\/\/dls03qes9fc77.cloudfront.net\/api\/auth\/me",
							"method": "GET",
							"param": "",
							"attack": "",
							"evidence": "401",
							"otherinfo": ""
						},
						{
							"id": "210",
							"uri": "https://dls03qes9fc77.cloudfront.net/api/auth/me/",
							"nodeName": "https:\/\/dls03qes9fc77.cloudfront.net\/api\/auth\/me\/",
							"method": "GET",
							"param": "",
							"attack": "",
							"evidence": "404",
							"otherinfo": ""
						},
						{
							"id": "82",
							"uri": "https://dls03qes9fc77.cloudfront.net/api/catalog",
							"nodeName": "https:\/\/dls03qes9fc77.cloudfront.net\/api\/catalog",
							"method": "GET",
							"param": "",
							"attack": "",
							"evidence": "404",
							"otherinfo": ""
						},
						{
							"id": "211",
							"uri": "https://dls03qes9fc77.cloudfront.net/api/catalog/",
							"nodeName": "https:\/\/dls03qes9fc77.cloudfront.net\/api\/catalog\/",
							"method": "GET",
							"param": "",
							"attack": "",
							"evidence": "404",
							"otherinfo": ""
						},
						{
							"id": "69",
							"uri": "https://dls03qes9fc77.cloudfront.net/api/catalog/8808101987410777781",
							"nodeName": "https:\/\/dls03qes9fc77.cloudfront.net\/api\/catalog\/8808101987410777781",
							"method": "GET",
							"param": "",
							"attack": "",
							"evidence": "404",
							"otherinfo": ""
						},
						{
							"id": "213",
							"uri": "https://dls03qes9fc77.cloudfront.net/api/catalog/categories/",
							"nodeName": "https:\/\/dls03qes9fc77.cloudfront.net\/api\/catalog\/categories\/",
							"method": "GET",
							"param": "",
							"attack": "",
							"evidence": "404",
							"otherinfo": ""
						},
						{
							"id": "70",
							"uri": "https://dls03qes9fc77.cloudfront.net/api/catalog/categories/4719963956595480336",
							"nodeName": "https:\/\/dls03qes9fc77.cloudfront.net\/api\/catalog\/categories\/4719963956595480336",
							"method": "GET",
							"param": "",
							"attack": "",
							"evidence": "404",
							"otherinfo": ""
						},
						{
							"id": "38",
							"uri": "https://dls03qes9fc77.cloudfront.net/api/catalog/categories/idOrSlug",
							"nodeName": "https:\/\/dls03qes9fc77.cloudfront.net\/api\/catalog\/categories\/idOrSlug",
							"method": "GET",
							"param": "",
							"attack": "",
							"evidence": "404",
							"otherinfo": ""
						},
						{
							"id": "214",
							"uri": "https://dls03qes9fc77.cloudfront.net/api/catalog/categories/idOrSlug/",
							"nodeName": "https:\/\/dls03qes9fc77.cloudfront.net\/api\/catalog\/categories\/idOrSlug\/",
							"method": "GET",
							"param": "",
							"attack": "",
							"evidence": "404",
							"otherinfo": ""
						},
						{
							"id": "212",
							"uri": "https://dls03qes9fc77.cloudfront.net/api/catalog/products/",
							"nodeName": "https:\/\/dls03qes9fc77.cloudfront.net\/api\/catalog\/products\/",
							"method": "GET",
							"param": "",
							"attack": "",
							"evidence": "404",
							"otherinfo": ""
						},
						{
							"id": "71",
							"uri": "https://dls03qes9fc77.cloudfront.net/api/catalog/products/8494058465729906530",
							"nodeName": "https:\/\/dls03qes9fc77.cloudfront.net\/api\/catalog\/products\/8494058465729906530",
							"method": "GET",
							"param": "",
							"attack": "",
							"evidence": "404",
							"otherinfo": ""
						},
						{
							"id": "42",
							"uri": "https://dls03qes9fc77.cloudfront.net/api/catalog/products/idOrSlug",
							"nodeName": "https:\/\/dls03qes9fc77.cloudfront.net\/api\/catalog\/products\/idOrSlug",
							"method": "GET",
							"param": "",
							"attack": "",
							"evidence": "404",
							"otherinfo": ""
						},
						{
							"id": "215",
							"uri": "https://dls03qes9fc77.cloudfront.net/api/catalog/products/idOrSlug/",
							"nodeName": "https:\/\/dls03qes9fc77.cloudfront.net\/api\/catalog\/products\/idOrSlug\/",
							"method": "GET",
							"param": "",
							"attack": "",
							"evidence": "404",
							"otherinfo": ""
						},
						{
							"id": "72",
							"uri": "https://dls03qes9fc77.cloudfront.net/api/docs/836015919180564872",
							"nodeName": "https:\/\/dls03qes9fc77.cloudfront.net\/api\/docs\/836015919180564872",
							"method": "GET",
							"param": "",
							"attack": "",
							"evidence": "404",
							"otherinfo": ""
						},
						{
							"id": "216",
							"uri": "https://dls03qes9fc77.cloudfront.net/api/docs/json/",
							"nodeName": "https:\/\/dls03qes9fc77.cloudfront.net\/api\/docs\/json\/",
							"method": "GET",
							"param": "",
							"attack": "",
							"evidence": "404",
							"otherinfo": ""
						},
						{
							"id": "83",
							"uri": "https://dls03qes9fc77.cloudfront.net/api/orders",
							"nodeName": "https:\/\/dls03qes9fc77.cloudfront.net\/api\/orders",
							"method": "GET",
							"param": "",
							"attack": "",
							"evidence": "401",
							"otherinfo": ""
						},
						{
							"id": "56",
							"uri": "https://dls03qes9fc77.cloudfront.net/api/orders/",
							"nodeName": "https:\/\/dls03qes9fc77.cloudfront.net\/api\/orders\/",
							"method": "GET",
							"param": "",
							"attack": "",
							"evidence": "401",
							"otherinfo": ""
						},
						{
							"id": "73",
							"uri": "https://dls03qes9fc77.cloudfront.net/api/orders/913585119119341658",
							"nodeName": "https:\/\/dls03qes9fc77.cloudfront.net\/api\/orders\/913585119119341658",
							"method": "GET",
							"param": "",
							"attack": "",
							"evidence": "401",
							"otherinfo": ""
						},
						{
							"id": "84",
							"uri": "https://dls03qes9fc77.cloudfront.net/api/orders/admin",
							"nodeName": "https:\/\/dls03qes9fc77.cloudfront.net\/api\/orders\/admin",
							"method": "GET",
							"param": "",
							"attack": "",
							"evidence": "401",
							"otherinfo": ""
						},
						{
							"id": "224",
							"uri": "https://dls03qes9fc77.cloudfront.net/api/orders/admin/",
							"nodeName": "https:\/\/dls03qes9fc77.cloudfront.net\/api\/orders\/admin\/",
							"method": "GET",
							"param": "",
							"attack": "",
							"evidence": "404",
							"otherinfo": ""
						},
						{
							"id": "74",
							"uri": "https://dls03qes9fc77.cloudfront.net/api/orders/admin/8908923351233057963",
							"nodeName": "https:\/\/dls03qes9fc77.cloudfront.net\/api\/orders\/admin\/8908923351233057963",
							"method": "GET",
							"param": "",
							"attack": "",
							"evidence": "404",
							"otherinfo": ""
						},
						{
							"id": "60",
							"uri": "https://dls03qes9fc77.cloudfront.net/api/orders/admin/all",
							"nodeName": "https:\/\/dls03qes9fc77.cloudfront.net\/api\/orders\/admin\/all",
							"method": "GET",
							"param": "",
							"attack": "",
							"evidence": "401",
							"otherinfo": ""
						},
						{
							"id": "223",
							"uri": "https://dls03qes9fc77.cloudfront.net/api/orders/admin/all/",
							"nodeName": "https:\/\/dls03qes9fc77.cloudfront.net\/api\/orders\/admin\/all\/",
							"method": "GET",
							"param": "",
							"attack": "",
							"evidence": "404",
							"otherinfo": ""
						},
						{
							"id": "62",
							"uri": "https://dls03qes9fc77.cloudfront.net/api/orders/admin/stats",
							"nodeName": "https:\/\/dls03qes9fc77.cloudfront.net\/api\/orders\/admin\/stats",
							"method": "GET",
							"param": "",
							"attack": "",
							"evidence": "401",
							"otherinfo": ""
						},
						{
							"id": "222",
							"uri": "https://dls03qes9fc77.cloudfront.net/api/orders/admin/stats/",
							"nodeName": "https:\/\/dls03qes9fc77.cloudfront.net\/api\/orders\/admin\/stats\/",
							"method": "GET",
							"param": "",
							"attack": "",
							"evidence": "404",
							"otherinfo": ""
						},
						{
							"id": "58",
							"uri": "https://dls03qes9fc77.cloudfront.net/api/orders/id",
							"nodeName": "https:\/\/dls03qes9fc77.cloudfront.net\/api\/orders\/id",
							"method": "GET",
							"param": "",
							"attack": "",
							"evidence": "401",
							"otherinfo": ""
						},
						{
							"id": "226",
							"uri": "https://dls03qes9fc77.cloudfront.net/api/orders/id/",
							"nodeName": "https:\/\/dls03qes9fc77.cloudfront.net\/api\/orders\/id\/",
							"method": "GET",
							"param": "",
							"attack": "",
							"evidence": "404",
							"otherinfo": ""
						},
						{
							"id": "75",
							"uri": "https://dls03qes9fc77.cloudfront.net/api/orders/id/3074349547844201289",
							"nodeName": "https:\/\/dls03qes9fc77.cloudfront.net\/api\/orders\/id\/3074349547844201289",
							"method": "GET",
							"param": "",
							"attack": "",
							"evidence": "404",
							"otherinfo": ""
						},
						{
							"id": "85",
							"uri": "https://dls03qes9fc77.cloudfront.net/api/search",
							"nodeName": "https:\/\/dls03qes9fc77.cloudfront.net\/api\/search",
							"method": "GET",
							"param": "",
							"attack": "",
							"evidence": "422",
							"otherinfo": ""
						},
						{
							"id": "54",
							"uri": "https://dls03qes9fc77.cloudfront.net/api/search/",
							"nodeName": "https:\/\/dls03qes9fc77.cloudfront.net\/api\/search\/",
							"method": "GET",
							"param": "",
							"attack": "",
							"evidence": "422",
							"otherinfo": ""
						},
						{
							"id": "76",
							"uri": "https://dls03qes9fc77.cloudfront.net/api/search/1791989588455378668",
							"nodeName": "https:\/\/dls03qes9fc77.cloudfront.net\/api\/search\/1791989588455378668",
							"method": "GET",
							"param": "",
							"attack": "",
							"evidence": "404",
							"otherinfo": ""
						},
						{
							"id": "284",
							"uri": "https://dls03qes9fc77.cloudfront.net/api/search/actuator/health",
							"nodeName": "https:\/\/dls03qes9fc77.cloudfront.net\/api\/search\/actuator\/health",
							"method": "GET",
							"param": "",
							"attack": "",
							"evidence": "404",
							"otherinfo": ""
						},
						{
							"id": "227",
							"uri": "https://dls03qes9fc77.cloudfront.net/api/search/popular/",
							"nodeName": "https:\/\/dls03qes9fc77.cloudfront.net\/api\/search\/popular\/",
							"method": "GET",
							"param": "",
							"attack": "",
							"evidence": "404",
							"otherinfo": ""
						},
						{
							"id": "55",
							"uri": "https://dls03qes9fc77.cloudfront.net/api/search/suggest",
							"nodeName": "https:\/\/dls03qes9fc77.cloudfront.net\/api\/search\/suggest",
							"method": "GET",
							"param": "",
							"attack": "",
							"evidence": "422",
							"otherinfo": ""
						},
						{
							"id": "228",
							"uri": "https://dls03qes9fc77.cloudfront.net/api/search/suggest/",
							"nodeName": "https:\/\/dls03qes9fc77.cloudfront.net\/api\/search\/suggest\/",
							"method": "GET",
							"param": "",
							"attack": "",
							"evidence": "404",
							"otherinfo": ""
						},
						{
							"id": "155",
							"uri": "https://dls03qes9fc77.cloudfront.net/computeMetadata/v1/",
							"nodeName": "https:\/\/dls03qes9fc77.cloudfront.net\/computeMetadata\/v1\/",
							"method": "GET",
							"param": "",
							"attack": "",
							"evidence": "403",
							"otherinfo": ""
						},
						{
							"id": "2",
							"uri": "https://dls03qes9fc77.cloudfront.net/health",
							"nodeName": "https:\/\/dls03qes9fc77.cloudfront.net\/health",
							"method": "GET",
							"param": "",
							"attack": "",
							"evidence": "404",
							"otherinfo": ""
						},
						{
							"id": "234",
							"uri": "https://dls03qes9fc77.cloudfront.net/health/",
							"nodeName": "https:\/\/dls03qes9fc77.cloudfront.net\/health\/",
							"method": "GET",
							"param": "",
							"attack": "",
							"evidence": "404",
							"otherinfo": ""
						},
						{
							"id": "151",
							"uri": "https://dls03qes9fc77.cloudfront.net/latest/meta-data/",
							"nodeName": "https:\/\/dls03qes9fc77.cloudfront.net\/latest\/meta-data\/",
							"method": "GET",
							"param": "",
							"attack": "",
							"evidence": "403",
							"otherinfo": ""
						},
						{
							"id": "167",
							"uri": "https://dls03qes9fc77.cloudfront.net/metadata/instance",
							"nodeName": "https:\/\/dls03qes9fc77.cloudfront.net\/metadata\/instance",
							"method": "GET",
							"param": "",
							"attack": "",
							"evidence": "403",
							"otherinfo": ""
						},
						{
							"id": "86",
							"uri": "https://dls03qes9fc77.cloudfront.net/metrics",
							"nodeName": "https:\/\/dls03qes9fc77.cloudfront.net\/metrics",
							"method": "GET",
							"param": "",
							"attack": "",
							"evidence": "404",
							"otherinfo": ""
						},
						{
							"id": "246",
							"uri": "https://dls03qes9fc77.cloudfront.net/metrics/",
							"nodeName": "https:\/\/dls03qes9fc77.cloudfront.net\/metrics\/",
							"method": "GET",
							"param": "",
							"attack": "",
							"evidence": "404",
							"otherinfo": ""
						},
						{
							"id": "77",
							"uri": "https://dls03qes9fc77.cloudfront.net/metrics/4835326925883131267",
							"nodeName": "https:\/\/dls03qes9fc77.cloudfront.net\/metrics\/4835326925883131267",
							"method": "GET",
							"param": "",
							"attack": "",
							"evidence": "404",
							"otherinfo": ""
						},
						{
							"id": "6",
							"uri": "https://dls03qes9fc77.cloudfront.net/metrics/cache",
							"nodeName": "https:\/\/dls03qes9fc77.cloudfront.net\/metrics\/cache",
							"method": "GET",
							"param": "",
							"attack": "",
							"evidence": "404",
							"otherinfo": ""
						},
						{
							"id": "242",
							"uri": "https://dls03qes9fc77.cloudfront.net/metrics/cache/",
							"nodeName": "https:\/\/dls03qes9fc77.cloudfront.net\/metrics\/cache\/",
							"method": "GET",
							"param": "",
							"attack": "",
							"evidence": "404",
							"otherinfo": ""
						},
						{
							"id": "159",
							"uri": "https://dls03qes9fc77.cloudfront.net/opc/v1/instance/",
							"nodeName": "https:\/\/dls03qes9fc77.cloudfront.net\/opc\/v1\/instance\/",
							"method": "GET",
							"param": "",
							"attack": "",
							"evidence": "403",
							"otherinfo": ""
						},
						{
							"id": "4",
							"uri": "https://dls03qes9fc77.cloudfront.net/ready",
							"nodeName": "https:\/\/dls03qes9fc77.cloudfront.net\/ready",
							"method": "GET",
							"param": "",
							"attack": "",
							"evidence": "404",
							"otherinfo": ""
						},
						{
							"id": "238",
							"uri": "https://dls03qes9fc77.cloudfront.net/ready/",
							"nodeName": "https:\/\/dls03qes9fc77.cloudfront.net\/ready\/",
							"method": "GET",
							"param": "",
							"attack": "",
							"evidence": "404",
							"otherinfo": ""
						},
						{
							"id": "11",
							"uri": "https://dls03qes9fc77.cloudfront.net/api/auth/me",
							"nodeName": "https:\/\/dls03qes9fc77.cloudfront.net\/api\/auth\/me",
							"method": "PATCH",
							"param": "",
							"attack": "",
							"evidence": "401",
							"otherinfo": ""
						},
						{
							"id": "195",
							"uri": "https://dls03qes9fc77.cloudfront.net/api/auth/me/",
							"nodeName": "https:\/\/dls03qes9fc77.cloudfront.net\/api\/auth\/me\/",
							"method": "PATCH",
							"param": "",
							"attack": "",
							"evidence": "404",
							"otherinfo": ""
						},
						{
							"id": "40",
							"uri": "https://dls03qes9fc77.cloudfront.net/api/catalog/categories/id",
							"nodeName": "https:\/\/dls03qes9fc77.cloudfront.net\/api\/catalog\/categories\/id",
							"method": "PATCH",
							"param": "",
							"attack": "",
							"evidence": "401",
							"otherinfo": ""
						},
						{
							"id": "197",
							"uri": "https://dls03qes9fc77.cloudfront.net/api/catalog/categories/id/",
							"nodeName": "https:\/\/dls03qes9fc77.cloudfront.net\/api\/catalog\/categories\/id\/",
							"method": "PATCH",
							"param": "",
							"attack": "",
							"evidence": "404",
							"otherinfo": ""
						},
						{
							"id": "48",
							"uri": "https://dls03qes9fc77.cloudfront.net/api/catalog/products/id",
							"nodeName": "https:\/\/dls03qes9fc77.cloudfront.net\/api\/catalog\/products\/id",
							"method": "PATCH",
							"param": "",
							"attack": "",
							"evidence": "401",
							"otherinfo": ""
						},
						{
							"id": "199",
							"uri": "https://dls03qes9fc77.cloudfront.net/api/catalog/products/id/",
							"nodeName": "https:\/\/dls03qes9fc77.cloudfront.net\/api\/catalog\/products\/id\/",
							"method": "PATCH",
							"param": "",
							"attack": "",
							"evidence": "404",
							"otherinfo": ""
						},
						{
							"id": "61",
							"uri": "https://dls03qes9fc77.cloudfront.net/api/orders/id/status",
							"nodeName": "https:\/\/dls03qes9fc77.cloudfront.net\/api\/orders\/id\/status",
							"method": "PATCH",
							"param": "",
							"attack": "",
							"evidence": "401",
							"otherinfo": ""
						},
						{
							"id": "202",
							"uri": "https://dls03qes9fc77.cloudfront.net/api/orders/id/status/",
							"nodeName": "https:\/\/dls03qes9fc77.cloudfront.net\/api\/orders\/id\/status\/",
							"method": "PATCH",
							"param": "",
							"attack": "",
							"evidence": "404",
							"otherinfo": ""
						},
						{
							"id": "12",
							"uri": "https://dls03qes9fc77.cloudfront.net/api/auth/change-password",
							"nodeName": "https:\/\/dls03qes9fc77.cloudfront.net\/api\/auth\/change-password",
							"method": "POST",
							"param": "",
							"attack": "",
							"evidence": "401",
							"otherinfo": ""
						},
						{
							"id": "188",
							"uri": "https://dls03qes9fc77.cloudfront.net/api/auth/change-password/",
							"nodeName": "https:\/\/dls03qes9fc77.cloudfront.net\/api\/auth\/change-password\/",
							"method": "POST",
							"param": "",
							"attack": "",
							"evidence": "404",
							"otherinfo": ""
						},
						{
							"id": "9",
							"uri": "https://dls03qes9fc77.cloudfront.net/api/auth/login",
							"nodeName": "https:\/\/dls03qes9fc77.cloudfront.net\/api\/auth\/login",
							"method": "POST",
							"param": "",
							"attack": "",
							"evidence": "422",
							"otherinfo": ""
						},
						{
							"id": "189",
							"uri": "https://dls03qes9fc77.cloudfront.net/api/auth/login/",
							"nodeName": "https:\/\/dls03qes9fc77.cloudfront.net\/api\/auth\/login\/",
							"method": "POST",
							"param": "",
							"attack": "",
							"evidence": "404",
							"otherinfo": ""
						},
						{
							"id": "20",
							"uri": "https://dls03qes9fc77.cloudfront.net/api/auth/logout",
							"nodeName": "https:\/\/dls03qes9fc77.cloudfront.net\/api\/auth\/logout",
							"method": "POST",
							"param": "",
							"attack": "",
							"evidence": "401",
							"otherinfo": ""
						},
						{
							"id": "191",
							"uri": "https://dls03qes9fc77.cloudfront.net/api/auth/logout/",
							"nodeName": "https:\/\/dls03qes9fc77.cloudfront.net\/api\/auth\/logout\/",
							"method": "POST",
							"param": "",
							"attack": "",
							"evidence": "404",
							"otherinfo": ""
						},
						{
							"id": "8",
							"uri": "https://dls03qes9fc77.cloudfront.net/api/auth/register",
							"nodeName": "https:\/\/dls03qes9fc77.cloudfront.net\/api\/auth\/register",
							"method": "POST",
							"param": "",
							"attack": "",
							"evidence": "422",
							"otherinfo": ""
						},
						{
							"id": "194",
							"uri": "https://dls03qes9fc77.cloudfront.net/api/auth/register/",
							"nodeName": "https:\/\/dls03qes9fc77.cloudfront.net\/api\/auth\/register\/",
							"method": "POST",
							"param": "",
							"attack": "",
							"evidence": "404",
							"otherinfo": ""
						},
						{
							"id": "37",
							"uri": "https://dls03qes9fc77.cloudfront.net/api/catalog/categories",
							"nodeName": "https:\/\/dls03qes9fc77.cloudfront.net\/api\/catalog\/categories",
							"method": "POST",
							"param": "",
							"attack": "",
							"evidence": "401",
							"otherinfo": ""
						},
						{
							"id": "193",
							"uri": "https://dls03qes9fc77.cloudfront.net/api/catalog/categories/",
							"nodeName": "https:\/\/dls03qes9fc77.cloudfront.net\/api\/catalog\/categories\/",
							"method": "POST",
							"param": "",
							"attack": "",
							"evidence": "404",
							"otherinfo": ""
						},
						{
							"id": "41",
							"uri": "https://dls03qes9fc77.cloudfront.net/api/catalog/products",
							"nodeName": "https:\/\/dls03qes9fc77.cloudfront.net\/api\/catalog\/products",
							"method": "POST",
							"param": "",
							"attack": "",
							"evidence": "401",
							"otherinfo": ""
						},
						{
							"id": "196",
							"uri": "https://dls03qes9fc77.cloudfront.net/api/catalog/products/",
							"nodeName": "https:\/\/dls03qes9fc77.cloudfront.net\/api\/catalog\/products\/",
							"method": "POST",
							"param": "",
							"attack": "",
							"evidence": "404",
							"otherinfo": ""
						},
						{
							"id": "57",
							"uri": "https://dls03qes9fc77.cloudfront.net/api/orders/",
							"nodeName": "https:\/\/dls03qes9fc77.cloudfront.net\/api\/orders\/",
							"method": "POST",
							"param": "",
							"attack": "",
							"evidence": "401",
							"otherinfo": ""
						},
						{
							"id": "59",
							"uri": "https://dls03qes9fc77.cloudfront.net/api/orders/id/cancel",
							"nodeName": "https:\/\/dls03qes9fc77.cloudfront.net\/api\/orders\/id\/cancel",
							"method": "POST",
							"param": "",
							"attack": "",
							"evidence": "401",
							"otherinfo": ""
						},
						{
							"id": "201",
							"uri": "https://dls03qes9fc77.cloudfront.net/api/orders/id/cancel/",
							"nodeName": "https:\/\/dls03qes9fc77.cloudfront.net\/api\/orders\/id\/cancel\/",
							"method": "POST",
							"param": "",
							"attack": "",
							"evidence": "404",
							"otherinfo": ""
						}
					],
					"count": "82",
					"systemic": false,
					"solution": "",
					"otherinfo": "",
					"reference": "",
					"cweid": "388",
					"wascid": "20",
					"sourceid": "21"
				},
				{
					"pluginid": "10109",
					"alertRef": "10109",
					"alert": "Modern Web Application",
					"name": "Modern Web Application",
					"riskcode": "0",
					"confidence": "2",
					"riskdesc": "Informational (Medium)",
					"desc": "<p>The application appears to be a modern web application. If you need to explore it automatically then the Ajax Spider may well be more effective than the standard one.</p>",
					"instances":[ 
						{
							"id": "16",
							"uri": "https://dls03qes9fc77.cloudfront.net/health",
							"nodeName": "https:\/\/dls03qes9fc77.cloudfront.net\/health",
							"method": "GET",
							"param": "",
							"attack": "",
							"evidence": "<a href=\"#\" class=\"text-gray-400 hover:text-gray-600 transition-colors\" aria-label=\"Twitter\"><svg xmlns=\"http://www.w3.org/2000/svg\" width=\"24\" height=\"24\" viewBox=\"0 0 24 24\" fill=\"none\" stroke=\"currentColor\" stroke-width=\"2\" stroke-linecap=\"round\" stroke-linejoin=\"round\" class=\"lucide lucide-twitter w-5 h-5\"><path d=\"M22 4s-.7 2.1-2 3.4c1.6 10-9.4 17.3-18 11.6 2.2.1 4.4-.6 6-2C3 15.5.5 9.6 3 5c2.2 2.6 5.6 4.1 9 4-.9-4.2 4-6.6 7-3.8 1.1 0 3-1.2 3-1.2z\"></path></svg></a>",
							"otherinfo": "Links have been found that do not have traditional href attributes, which is an indication that this is a modern web application."
						},
						{
							"id": "29",
							"uri": "https://dls03qes9fc77.cloudfront.net/metrics/cache",
							"nodeName": "https:\/\/dls03qes9fc77.cloudfront.net\/metrics\/cache",
							"method": "GET",
							"param": "",
							"attack": "",
							"evidence": "<a href=\"#\" class=\"text-gray-400 hover:text-gray-600 transition-colors\" aria-label=\"Twitter\"><svg xmlns=\"http://www.w3.org/2000/svg\" width=\"24\" height=\"24\" viewBox=\"0 0 24 24\" fill=\"none\" stroke=\"currentColor\" stroke-width=\"2\" stroke-linecap=\"round\" stroke-linejoin=\"round\" class=\"lucide lucide-twitter w-5 h-5\"><path d=\"M22 4s-.7 2.1-2 3.4c1.6 10-9.4 17.3-18 11.6 2.2.1 4.4-.6 6-2C3 15.5.5 9.6 3 5c2.2 2.6 5.6 4.1 9 4-.9-4.2 4-6.6 7-3.8 1.1 0 3-1.2 3-1.2z\"></path></svg></a>",
							"otherinfo": "Links have been found that do not have traditional href attributes, which is an indication that this is a modern web application."
						},
						{
							"id": "15",
							"uri": "https://dls03qes9fc77.cloudfront.net/ready",
							"nodeName": "https:\/\/dls03qes9fc77.cloudfront.net\/ready",
							"method": "GET",
							"param": "",
							"attack": "",
							"evidence": "<a href=\"#\" class=\"text-gray-400 hover:text-gray-600 transition-colors\" aria-label=\"Twitter\"><svg xmlns=\"http://www.w3.org/2000/svg\" width=\"24\" height=\"24\" viewBox=\"0 0 24 24\" fill=\"none\" stroke=\"currentColor\" stroke-width=\"2\" stroke-linecap=\"round\" stroke-linejoin=\"round\" class=\"lucide lucide-twitter w-5 h-5\"><path d=\"M22 4s-.7 2.1-2 3.4c1.6 10-9.4 17.3-18 11.6 2.2.1 4.4-.6 6-2C3 15.5.5 9.6 3 5c2.2 2.6 5.6 4.1 9 4-.9-4.2 4-6.6 7-3.8 1.1 0 3-1.2 3-1.2z\"></path></svg></a>",
							"otherinfo": "Links have been found that do not have traditional href attributes, which is an indication that this is a modern web application."
						}
					],
					"count": "3",
					"systemic": true,
					"solution": "<p>This is an informational alert and so no changes are required.</p>",
					"otherinfo": "<p>Links have been found that do not have traditional href attributes, which is an indication that this is a modern web application.</p>",
					"reference": "",
					"cweid": "-1",
					"wascid": "-1",
					"sourceid": "5"
				},
				{
					"pluginid": "10049",
					"alertRef": "10049-1",
					"alert": "Non-Storable Content",
					"name": "Non-Storable Content",
					"riskcode": "0",
					"confidence": "2",
					"riskdesc": "Informational (Medium)",
					"desc": "<p>The response contents are not storable by caching components such as proxy servers. If the response does not contain sensitive, personal or user-specific information, it may benefit from being stored and cached, to improve performance.</p>",
					"instances":[ 
						{
							"id": "31",
							"uri": "https://dls03qes9fc77.cloudfront.net/api/auth/me",
							"nodeName": "https:\/\/dls03qes9fc77.cloudfront.net\/api\/auth\/me",
							"method": "GET",
							"param": "",
							"attack": "",
							"evidence": "401",
							"otherinfo": ""
						},
						{
							"id": "23",
							"uri": "https://dls03qes9fc77.cloudfront.net/health",
							"nodeName": "https:\/\/dls03qes9fc77.cloudfront.net\/health",
							"method": "GET",
							"param": "",
							"attack": "",
							"evidence": "no-store",
							"otherinfo": ""
						},
						{
							"id": "22",
							"uri": "https://dls03qes9fc77.cloudfront.net/ready",
							"nodeName": "https:\/\/dls03qes9fc77.cloudfront.net\/ready",
							"method": "GET",
							"param": "",
							"attack": "",
							"evidence": "no-store",
							"otherinfo": ""
						},
						{
							"id": "28",
							"uri": "https://dls03qes9fc77.cloudfront.net/api/auth/login",
							"nodeName": "https:\/\/dls03qes9fc77.cloudfront.net\/api\/auth\/login",
							"method": "POST",
							"param": "",
							"attack": "",
							"evidence": "422",
							"otherinfo": ""
						},
						{
							"id": "27",
							"uri": "https://dls03qes9fc77.cloudfront.net/api/auth/register",
							"nodeName": "https:\/\/dls03qes9fc77.cloudfront.net\/api\/auth\/register",
							"method": "POST",
							"param": "",
							"attack": "",
							"evidence": "422",
							"otherinfo": ""
						}
					],
					"count": "5",
					"systemic": true,
					"solution": "<p>The content may be marked as storable by ensuring that the following conditions are satisfied:</p><p>The request method must be understood by the cache and defined as being cacheable (\"GET\", \"HEAD\", and \"POST\" are currently defined as cacheable)</p><p>The response status code must be understood by the cache (one of the 1XX, 2XX, 3XX, 4XX, or 5XX response classes are generally understood)</p><p>The \"no-store\" cache directive must not appear in the request or response header fields</p><p>For caching by \"shared\" caches such as \"proxy\" caches, the \"private\" response directive must not appear in the response</p><p>For caching by \"shared\" caches such as \"proxy\" caches, the \"Authorization\" header field must not appear in the request, unless the response explicitly allows it (using one of the \"must-revalidate\", \"public\", or \"s-maxage\" Cache-Control response directives)</p><p>In addition to the conditions above, at least one of the following conditions must also be satisfied by the response:</p><p>It must contain an \"Expires\" header field</p><p>It must contain a \"max-age\" response directive</p><p>For \"shared\" caches such as \"proxy\" caches, it must contain a \"s-maxage\" response directive</p><p>It must contain a \"Cache Control Extension\" that allows it to be cached</p><p>It must have a status code that is defined as cacheable by default (200, 203, 204, 206, 300, 301, 404, 405, 410, 414, 501).</p>",
					"otherinfo": "",
					"reference": "<p>https://datatracker.ietf.org/doc/html/rfc7234</p><p>https://datatracker.ietf.org/doc/html/rfc7231</p><p>https://www.w3.org/Protocols/rfc2616/rfc2616-sec13.html</p>",
					"cweid": "524",
					"wascid": "13",
					"sourceid": "12"
				},
				{
					"pluginid": "10015",
					"alertRef": "10015",
					"alert": "Re-examine Cache-control Directives",
					"name": "Re-examine Cache-control Directives",
					"riskcode": "0",
					"confidence": "1",
					"riskdesc": "Informational (Low)",
					"desc": "<p>The cache-control header has not been set properly or is missing, allowing the browser and proxies to cache content. For static assets like css, js, or image files this might be intended, however, the resources should be reviewed to ensure that no sensitive content will be cached.</p>",
					"instances":[ 
						{
							"id": "44",
							"uri": "https://dls03qes9fc77.cloudfront.net/api/catalog/categories",
							"nodeName": "https:\/\/dls03qes9fc77.cloudfront.net\/api\/catalog\/categories",
							"method": "GET",
							"param": "cache-control",
							"attack": "",
							"evidence": "",
							"otherinfo": ""
						},
						{
							"id": "49",
							"uri": "https://dls03qes9fc77.cloudfront.net/api/catalog/products",
							"nodeName": "https:\/\/dls03qes9fc77.cloudfront.net\/api\/catalog\/products",
							"method": "GET",
							"param": "cache-control",
							"attack": "",
							"evidence": "",
							"otherinfo": ""
						},
						{
							"id": "0",
							"uri": "https://dls03qes9fc77.cloudfront.net/api/docs/json",
							"nodeName": "https:\/\/dls03qes9fc77.cloudfront.net\/api\/docs\/json",
							"method": "GET",
							"param": "cache-control",
							"attack": "",
							"evidence": "",
							"otherinfo": ""
						},
						{
							"id": "64",
							"uri": "https://dls03qes9fc77.cloudfront.net/api/search/popular",
							"nodeName": "https:\/\/dls03qes9fc77.cloudfront.net\/api\/search\/popular",
							"method": "GET",
							"param": "cache-control",
							"attack": "",
							"evidence": "",
							"otherinfo": ""
						}
					],
					"count": "4",
					"systemic": true,
					"solution": "<p>For secure content, ensure the cache-control HTTP header is set with \"no-cache, no-store, must-revalidate\". If an asset should be cached consider setting the directives \"public, max-age, immutable\".</p>",
					"otherinfo": "",
					"reference": "<p>https://cheatsheetseries.owasp.org/cheatsheets/Session_Management_Cheat_Sheet.html#web-content-caching</p><p>https://developer.mozilla.org/en-US/docs/Web/HTTP/Reference/Headers/Cache-Control</p><p>https://grayduck.mn/2021/09/13/cache-control-recommendations/</p>",
					"cweid": "525",
					"wascid": "13",
					"sourceid": "16"
				},
				{
					"pluginid": "10049",
					"alertRef": "10049-3",
					"alert": "Storable and Cacheable Content",
					"name": "Storable and Cacheable Content",
					"riskcode": "0",
					"confidence": "2",
					"riskdesc": "Informational (Medium)",
					"desc": "<p>The response contents are storable by caching components such as proxy servers, and may be retrieved directly from the cache, rather than from the origin server by the caching servers, in response to similar requests from other users. If the response data is sensitive, personal or user-specific, this may result in sensitive information being leaked. In some cases, this may even result in a user gaining complete control of the session of another user, depending on the configuration of the caching components in use in their environment. This is primarily an issue where \"shared\" caching servers such as \"proxy\" caches are configured on the local network. This configuration is typically found in corporate or educational environments, for instance.</p>",
					"instances":[ 
						{
							"id": "47",
							"uri": "https://dls03qes9fc77.cloudfront.net/api/catalog/categories/idOrSlug",
							"nodeName": "https:\/\/dls03qes9fc77.cloudfront.net\/api\/catalog\/categories\/idOrSlug",
							"method": "GET",
							"param": "",
							"attack": "",
							"evidence": "",
							"otherinfo": "In the absence of an explicitly specified caching lifetime directive in the response, a liberal lifetime heuristic of 1 year was assumed. This is permitted by rfc7234."
						},
						{
							"id": "1",
							"uri": "https://dls03qes9fc77.cloudfront.net/api/docs/json",
							"nodeName": "https:\/\/dls03qes9fc77.cloudfront.net\/api\/docs\/json",
							"method": "GET",
							"param": "",
							"attack": "",
							"evidence": "",
							"otherinfo": "In the absence of an explicitly specified caching lifetime directive in the response, a liberal lifetime heuristic of 1 year was assumed. This is permitted by rfc7234."
						}
					],
					"count": "2",
					"systemic": true,
					"solution": "<p>Validate that the response does not contain sensitive, personal or user-specific information. If it does, consider the use of the following HTTP response headers, to limit, or prevent the content being stored and retrieved from the cache by another user:</p><p>Cache-Control: no-cache, no-store, must-revalidate, private</p><p>Pragma: no-cache</p><p>Expires: 0</p><p>This configuration directs both HTTP 1.0 and HTTP 1.1 compliant caching servers to not store the response, and to not retrieve the response (without validation) from the cache, in response to a similar request.</p>",
					"otherinfo": "<p>In the absence of an explicitly specified caching lifetime directive in the response, a liberal lifetime heuristic of 1 year was assumed. This is permitted by rfc7234.</p>",
					"reference": "<p>https://datatracker.ietf.org/doc/html/rfc7234</p><p>https://datatracker.ietf.org/doc/html/rfc7231</p><p>https://www.w3.org/Protocols/rfc2616/rfc2616-sec13.html</p>",
					"cweid": "524",
					"wascid": "13",
					"sourceid": "19"
				}
			]
		}
	],
	"sequences":[
	]

}
